vsutillib/log/__init__.py
vsutillib/log/classes/__init__.py
vsutillib/log/classes/logrotatehandler.py
vsutillib_log-1.6.0.dist-info/AUTHORS
vsutillib_log-1.6.0.dist-info/LICENSE.txt
vsutillib_log-1.6.0.dist-info/METADATA
vsutillib_log-1.6.0.dist-info/WHEEL
vsutillib_log-1.6.0.dist-info/top_level.txt
vsutillib_log-1.6.0.dist-info/RECORD
