Metadata-Version: 2.1
Name: vsutillib-log
Version: 1.6.0
Summary: vsutillib.log sub package part of vsutillib
Home-page: https://pypi.org/project/vsutillib-log/
Author: Efrain Vergara
Author-email: akai10tsuki@gmail.com
License: MIT
Platform: UNKNOWN
Requires-Python: >=3.8.1, <3.9
